squacapipy/__init__.py
squacapipy/errors.py
squacapipy/squacapi.py
squacapipy-0.4.dist-info/LICENSE
squacapipy-0.4.dist-info/METADATA
squacapipy-0.4.dist-info/WHEEL
squacapipy-0.4.dist-info/top_level.txt
squacapipy-0.4.dist-info/RECORD
