Metadata-Version: 2.1
Name: squacapipy
Version: 0.4
Summary: A python api wrapper for SQAUC API
Home-page: https://github.com/pnsn/squacapipy
Author: Jon Connolly
Author-email: joncon@uw.edu
License: UNKNOWN
Platform: UNKNOWN
Classifier: Programming Language :: Python :: 3
Classifier: License :: OSI Approved :: MIT License
Classifier: Operating System :: OS Independent
